snuffler/Snuffler.py
snuffler/__init__.py
snuffler-0.1.dist-info/LICENSE
snuffler-0.1.dist-info/METADATA
snuffler-0.1.dist-info/WHEEL
snuffler-0.1.dist-info/top_level.txt
snuffler-0.1.dist-info/RECORD
